ash2048/__init__.py
ash2048/env.py
ash2048/environment.py
ash2048/output.gif
ash2048-1.0.0.dist-info/METADATA
ash2048-1.0.0.dist-info/WHEEL
ash2048-1.0.0.dist-info/RECORD
